invenio_rest_api_client/__about__.py
invenio_rest_api_client/__init__.py
invenio_rest_api_client/client.py
invenio_rest_api_client/errors.py
invenio_rest_api_client/py.typed
invenio_rest_api_client/types.py
invenio_rest_api_client/api/__init__.py
invenio_rest_api_client/api/audit_logs/__init__.py
invenio_rest_api_client/api/audit_logs/retrieve_log_entry.py
invenio_rest_api_client/api/audit_logs/search_logs.py
invenio_rest_api_client/api/communities/__init__.py
invenio_rest_api_client/api/communities/create_a_community.py
invenio_rest_api_client/api/communities/delete_community.py
invenio_rest_api_client/api/communities/get_a_community.py
invenio_rest_api_client/api/communities/get_community_records.py
invenio_rest_api_client/api/communities/rename_a_community.py
invenio_rest_api_client/api/communities/search_communities.py
invenio_rest_api_client/api/communities/update_a_community.py
invenio_rest_api_client/api/communities_invitations/__init__.py
invenio_rest_api_client/api/communities_invitations/invite_user_members.py
invenio_rest_api_client/api/communities_invitations/search_invitations.py
invenio_rest_api_client/api/communities_invitations/update_invitations.py
invenio_rest_api_client/api/communities_logo/__init__.py
invenio_rest_api_client/api/communities_logo/delete_community_logo.py
invenio_rest_api_client/api/communities_logo/get_community_logo.py
invenio_rest_api_client/api/communities_logo/update_community_logo.py
invenio_rest_api_client/api/communities_members/__init__.py
invenio_rest_api_client/api/communities_members/add_group_members.py
invenio_rest_api_client/api/communities_members/remove_members_leave_community.py
invenio_rest_api_client/api/communities_members/search_members.py
invenio_rest_api_client/api/communities_members/search_public_members.py
invenio_rest_api_client/api/communities_members/update_members.py
invenio_rest_api_client/api/drafts/__init__.py
invenio_rest_api_client/api/drafts/createupdate_a_review_request.py
invenio_rest_api_client-12.0.1.dist-info/METADATA
invenio_rest_api_client-12.0.1.dist-info/WHEEL
invenio_rest_api_client-12.0.1.dist-info/RECORD
