Metadata-Version: 2.4
Name: invenio-rest-api-client
Version: 12.0.1
Summary: A client library for accessing Invenio REST API
Project-URL: Documentation, https://github.com/Terradue/invenio-rest-api-client#readme
Project-URL: Issues, https://github.com/Terradue/invenio-rest-api-client/issues
Project-URL: Source, https://github.com/Terradue/invenio-rest-api-client
Author-email: Fabrice Brito <info@terradue.com>, Simone Tripodi <info@terradue.com>
License-Expression: MIT
Classifier: Development Status :: 4 - Beta
Classifier: Programming Language :: Python
Classifier: Programming Language :: Python :: 3.8
Classifier: Programming Language :: Python :: 3.9
Classifier: Programming Language :: Python :: 3.10
Classifier: Programming Language :: Python :: 3.11
Classifier: Programming Language :: Python :: 3.12
Classifier: Programming Language :: Python :: Implementation :: CPython
Classifier: Programming Language :: Python :: Implementation :: PyPy
Requires-Python: >=3.8
Requires-Dist: attrs>=22.2.0
Requires-Dist: httpx<0.29.0,>=0.23.0
Requires-Dist: loguru
Requires-Dist: python-dateutil==2.8.0
